{
  "title": "15/05/2020 Закон за ратифициране на Шестия допълнителен протокол към Споразумението за Многонационалните мирни сили в Югоизточна Европа",
  "date": "",
  "link": "https://www.parliament.bg/bg/laws/ID/157373",
  "lawId": "157373",
  "actualTitle": "Закони",
  "metadata": [],
  "fullText": "ЗАКОН\n\nза ратифициране на Шестия допълнителен протокол към Споразумението за Многонационалните мирни сили в Югоизточна Европа\n\nЧлен единствен. \n\nРатифицира Шестия допълнителен протокол към Споразумението за Многонационалните мирни сили в Югоизточна Европа, подписан на 12 юни 2019 г. в Скопие, Република Северна Македония.\n\nЗаконът е приет от 44-то Народно събрание на 15 май 2020 г. и е подпечатан с официалния печат на Народното събрание.\n\nПредседател на Народното събрание:\n \nЦвета Караянчева\n\n3590",
  "textLength": 501,
  "scrapedAt": "2026-01-11T03:20:44.685Z",
  "isComplete": true,
  "error": null,
  "retryCount": 0
}