{
  "title": "15/09/2021 Закон за ратифициране на Тристранното споразумение за дарение на ваксини срещу COVID-19, произведени от АстраЗенека, между Република България, Босна и Херцеговина и АстраЗенека и на Двустранното споразумение за дарение на ваксини срещу COVID-19, произведени от АстраЗенека, между Република България и Босна и Херцеговина",
  "date": "",
  "link": "https://www.parliament.bg/bg/laws/ID/163821",
  "lawId": "163821",
  "actualTitle": "Закони",
  "metadata": [],
  "fullText": "ЗАКОН\n\nза ратифициране на Тристранното споразумение за дарение на ваксини срещу COVID-19, произведени от АстраЗенека, между Република България, Босна и Херцеговина и АстраЗенека и на Двустранното споразумение за дарение на ваксини срещу COVID-19, произведени от АстраЗенека, между Република България и Босна и Херцеговина\n\nЧл. 1. \n\nРатифицира Тристранното споразумение за дарение на ваксини срещу COVID-19, произведени от АстраЗенека, между Република България, Босна и Херцеговина и АстраЗенека, подписано от Република България на 6 август 2021 г. и от Босна и Херцеговина и от АстраЗенека на 9 август 2021 г., и Двустранното споразумение за дарение на ваксини срещу COVID-19, произведени от АстраЗенека, между Република България и Босна и Херцеговина, подписано от Република България на 6 август 2021 г. и от Босна и Херцеговина на 9 август 2021 г.\n\nЧл. 2. \n\nРазпорежда на основание чл. 25, ал. 2 от Закона за международните договори на Република България споразуменията по чл. 1 да не се обнародват в „Държавен вестник“.\n\nЗаконът е приет от 46-ото Народно събрание на 15 септември 2021 г. и е подпечатан с официалния печат на Народното събрание.\n\nПредседател на Народното събрание: \nИва Митева\n\n5618",
  "textLength": 1201,
  "scrapedAt": "2026-01-11T03:11:51.185Z",
  "isComplete": true,
  "error": null,
  "retryCount": 0
}