{
  "title": "12/09/2024 Закон за изменение и допълнение на Закона за физическото възпитание и спорта",
  "date": "",
  "link": "https://www.parliament.bg/bg/laws/ID/165727",
  "lawId": "165727",
  "actualTitle": "Закони",
  "metadata": [],
  "fullText": "ЗАКОН\n\nза изменение и допълнение на Закона за физическото възпитание и спорта \n\n(обн., ДВ, бр. 86 от 2018 г.; изм., бр. 17, 35 и 64 от 2019 г., бр. 69, 85 и 96 от 2020 г. и бр. 39 от 2024 г.)\n\nПараграф единствен.\n\n В чл. 136 се правят следните изменения и допълнения:\n\n1. В ал. 1:\n\nа) в т. 2:\n\nаа) в текста преди буква „а“ след думата „олимпийските“ се добавя „и паралимпийските“;\n\nбб) в буква „а“ след думата „олимпийския“ се добавя „или паралимпийския“;\n\nб) в т. 3 след думите „сборните олимпийски“ се добавя „и паралимпийски“.\n\n2. В ал. 3, изречение първо след думите „олимпийския медалист“ се поставя запетая и се добавя „съответно пред Националната паралимпийска организация от паралимпийския медалист“, а думите „когато олимпийският медалист“ се заменят с „когато медалистът“.\n\nЗаконът е приет от 50-ото Народно събрание на 12 септември 2024 г. и е подпечатан с официалния печат на Народното събрание.\n\nПредседател на Народното събрание:\n Рая Назарян\n\n6040",
  "textLength": 962,
  "scrapedAt": "2026-01-11T03:10:23.207Z",
  "isComplete": true,
  "error": null,
  "retryCount": 0
}