{
  "title": "13/01/2010 Закон за ратифициране на Петия допълнителен протокол към Споразумението за Многонационалните мирни сили в Югоизточна Европа",
  "date": "",
  "link": "https://www.parliament.bg/bg/laws/ID/9748",
  "lawId": "9748",
  "actualTitle": "Закони",
  "metadata": [],
  "fullText": "ЗАКОН\n\nза ратифициране на Петия допълнителен протокол към Споразумението за Многонационалните мирни сили в Югоизточна Европа\n\nЧлен единствен.\n\n Ратифицира Петия допълнителен протокол към Споразумението за Многонационалните мирни сили в Югоизточна Европа, подписан на 21 октомври 2009 г. в София.\n\nЗаконът е приет от 41-ото Народно събрание на 13 януари 2010 г. и е подпечатан с официалния печат на Народното събрание.\n\nПредседател на Народното събрание:\n  Цецка Цачева\n\n348",
  "textLength": 473,
  "scrapedAt": "2026-01-11T03:35:14.224Z",
  "isComplete": true,
  "error": null,
  "retryCount": 2
}